sphinx_enum_extend/__init__.py
sphinx_enum_extend/sphinx_enum_extend.py
sphinx_enum_extend-0.1.3.dist-info/LICENSE
sphinx_enum_extend-0.1.3.dist-info/METADATA
sphinx_enum_extend-0.1.3.dist-info/WHEEL
sphinx_enum_extend-0.1.3.dist-info/top_level.txt
sphinx_enum_extend-0.1.3.dist-info/RECORD
