Metadata-Version: 2.1
Name: sphinx-enum-extend
Version: 0.1.3
Summary: Spinx plugin for documenting enum-extend.AutoEnum
Home-page: https://github.com/Amourspirit/python-sphinx-enum-extend
Author: :Barry-Thomas-Paul: Moss
Author-email: bigbytetech@gmail.com
License: MIT
Keywords: python,enum,autoenum,sphinx,sphinx-extension,enum-docstring,enum-extend
Platform: UNKNOWN
Classifier: License :: OSI Approved :: MIT License
Classifier: Programming Language :: Python :: 3
Classifier: Programming Language :: Python :: 3.4
Classifier: Programming Language :: Python :: 3.5
Classifier: Programming Language :: Python :: 3.6
Classifier: Programming Language :: Python :: 3.7
Classifier: Programming Language :: Python :: 3.8
Classifier: Programming Language :: Python :: 3.9
Requires-Python: >=3.4.0
License-File: LICENSE
Requires-Dist: enum-extend (>=0.1.1)
